<?xml version="1.0" encoding="UTF-8"?>
<meta-runner name="meta metarunner with dot net tools">
  <description>meta metarunner with dot net tools</description>
  <settings>
    <parameters />
    <build-runners>
      <runner name="Net Inspections 2018.3.3" type="dotnet-tools-inspectcode">
        <parameters>
          <param name="dotnet-tools-inspectcode.solution" value="xxx.sln" />
          <param name="jetbrains.resharper-clt.clt-path" value="%teamcity.tool.jetbrains.resharper-clt.2018.3.3%" />
          <param name="jetbrains.resharper-clt.platform" value="x64" />
          <param name="teamcity.step.mode" value="default" />
        </parameters>
      </runner>
      <runner name="Default net inspections" type="dotnet-tools-inspectcode">
        <parameters>
          <param name="dotnet-tools-inspectcode.solution" value="xxx.sln" />
          <param name="jetbrains.resharper-clt.clt-path" value="%teamcity.tool.jetbrains.resharper-clt.DEFAULT%" />
          <param name="jetbrains.resharper-clt.platform" value="x64" />
          <param name="teamcity.step.mode" value="default" />
        </parameters>
      </runner>
    </build-runners>
    <requirements />
  </settings>
</meta-runner>

